pyjsoncfg/__init__.py
pyjsoncfg/__main__.py
pyjsoncfg/pyjsoncfg.py
pyjsoncfg/sample.py
pyjsoncfg-0.0.6.dist-info/LICENSE.md
pyjsoncfg-0.0.6.dist-info/METADATA
pyjsoncfg-0.0.6.dist-info/WHEEL
pyjsoncfg-0.0.6.dist-info/top_level.txt
pyjsoncfg-0.0.6.dist-info/RECORD
