Metadata-Version: 2.1
Name: pyjsoncfg
Version: 0.0.6
Summary: python json config file handling
Home-page: https://github.com/kr-g/pyjsoncfg
Author: k. goger
Author-email: k.r.goger+pyjsoncfg@gmail.com
License: MIT
Keywords: python config json
Platform: UNKNOWN
Classifier: Development Status :: 4 - Beta
Classifier: Operating System :: POSIX :: Linux
Classifier: Intended Audience :: Developers
Classifier: Programming Language :: Python :: 3
Classifier: License :: OSI Approved :: MIT License
Requires-Python: >=3.6
License-File: LICENSE.md
